src/__init__.py
src/cli.py
src/dijkstra.py
src/speech_to_txt.py
src/trip.py
src/utils.py
src/data/timetables.csv
src/data/timetables_test.csv
src/data/token_arrival.txt
src/data/token_depart.txt
src/data/token_etap.txt
nlp_900-1.0.0.dist-info/METADATA
nlp_900-1.0.0.dist-info/WHEEL
nlp_900-1.0.0.dist-info/entry_points.txt
nlp_900-1.0.0.dist-info/top_level.txt
nlp_900-1.0.0.dist-info/RECORD
