Metadata-Version: 2.1
Name: nlp-900
Version: 1.0.0
Summary: NLP
Home-page: https://gitlab.com/red-56/t9-nlp.git
License: UNKNOWN
Platform: UNKNOWN
Classifier: Development Status :: 5 - Production/Stable
Classifier: Environment :: Console
Classifier: Intended Audience :: Developers
Classifier: License :: OSI Approved :: MIT License
Classifier: Operating System :: OS Independent
Classifier: Programming Language :: Python :: 3
Classifier: Programming Language :: Python
Classifier: Programming Language :: Python :: 3 :: Only
Classifier: Programming Language :: Python :: 3.7
Classifier: Programming Language :: Python :: 3.8
Classifier: Programming Language :: Python :: 3.9
Requires-Python: >=3.7
Requires-Dist: click
Requires-Dist: vext
Requires-Dist: vext.gi
Requires-Dist: nltk
Requires-Dist: spacy
Requires-Dist: gTTS
Requires-Dist: playsound
Requires-Dist: SpeechRecognition
Requires-Dist: pyaudio
Requires-Dist: langdetect
